pycamt/__init__.py
pycamt/parser.py
pycamt-1.0.1.dist-info/LICENSE
pycamt-1.0.1.dist-info/METADATA
pycamt-1.0.1.dist-info/WHEEL
pycamt-1.0.1.dist-info/RECORD
