Metadata-Version: 2.1
Name: pycamt
Version: 1.0.1
Summary: Camt053Parser is a flexible and extensible Python class designed to parse CAMT.053 XML files, which are used for bank-to-customer account report messages in the financial industry. The parser supports multiple versions of the CAMT.053 standard, making it a versatile tool for extracting financial transaction data.
Home-page: https://github.com/ODAncona/pycamt
Author: Olivier D'Ancona
Author-email: folivier_dancona@hotmail.com
Requires-Python: >=3.8,<4.0
Classifier: Programming Language :: Python :: 3
Classifier: Programming Language :: Python :: 3.8
Classifier: Programming Language :: Python :: 3.9
Classifier: Programming Language :: Python :: 3.10
Classifier: Programming Language :: Python :: 3.11
Classifier: Programming Language :: Python :: 3.12
Requires-Dist: defusedxml (>=0.7.1,<0.8.0)
Project-URL: Documentation, https://ODAncona.github.io/pycamt/
Project-URL: Repository, https://github.com/ODAncona/pycamt
